{
    "CAPolicy": {
        "SNPolicy": {
            "AllowedCNs": [
                {
                    "type": "name",
                    "match": "constant",
                    "value": "localhost"
                },
                {
                    "type": "name",
                    "match": "req.hostname"
                },
                {
                    "type": "fqdn",
                    "match": "inzone"
                }
            ]
        },
        "SANPolicy": {
            "multiSAN": false,
            "AllowedSANs": [
                {
                    "type": "ip",
                    "match": "inzone"
                },
                {
                    "type": "name",
                    "match": "constant",
                    "value": "localhost"
                },
                {
                    "type": "name",
                    "match": "req.hostname"
                },
                {
                    "type": "fqdn",
                    "match": "inzone"
                }
            ]
        },
        "KeyUsagePolicy": {
            "AllowedKeyUsages": 255
        },
        "CertDurationPolicy": {
            "MaxAllowedDays" : 3650
        }
    },
    "CertificatePolicy": {
         "SNPolicy": {
            "AllowedCNs": [
                {
                    "type": "name",
                    "match": "constant",
                    "value": "localhost"
                },
                {
                    "type": "name",
                    "match": "req.hostname"
                },
                {
                    "type": "fqdn",
                    "match": "inzone"
                }
            ]
        },
        "SANPolicy": {
            "multiSAN": false,
            "AllowedSANs": [
                {
                    "type": "ip",
                    "match": "inzone"
                },
                {
                    "type": "name",
                    "match": "constant",
                    "value": "localhost"
                },
                {
                    "type": "name",
                    "match": "req.hostname"
                },
                {
                    "type": "fqdn",
                    "match": "inzone"
                }
            ]
        },
        "KeyUsagePolicy": {
            "AllowedKeyUsages": 255
        },
        "CertDurationPolicy": {
            "MaxAllowedDays" : 365
        }
    }
}
